{
  "Products": "Global Clean Energy ETF",
  "Ticker": "PBD",
  "Inception": "06/13/2007",
  "Gross Exp. Ratio": "0.75%",
  "YTD": "53.64",
  "1Yr": "82.39",
  "3Yr": "21.68",
  "5Yr": "17.78",
  "10Yr": "6.29",
  "Since Incept.": "0.14",
  "Category": "Thematic",
  "SubCategory": "Sustainable",
  "ticker": "PBD",
  "issuer": "Invesco",
  "website": "https://www.invesco.com/us/financial-products/etfs/product-detail?audienceType=Investor&ticker=PBD",
  "holdingDataSource": {
    "url": "https://www.invesco.com/us/financial-products/etfs/holdings/main/holdings/0?audienceType=Investor&action=download&ticker=PBD",
    "fileExt": "csv",
    "transform": "invesco"
  },
  "holdings": [
    {
      "ticker": "JKS",
      "name": "JinkoSolar Holding Co Ltd ADR",
      "percent": "3.038"
    },
    {
      "ticker": "DQ",
      "name": "Daqo New Energy Corp ADR",
      "percent": "1.699"
    },
    {
      "ticker": "ENPH",
      "name": "Enphase Energy Inc",
      "percent": "1.581"
    },
    {
      "ticker": "SPWR",
      "name": "SunPower Corp",
      "percent": "1.533"
    },
    {
      "ticker": "SEDG",
      "name": "SolarEdge Technologies Inc",
      "percent": "1.527"
    },
    {
      "ticker": "NIO",
      "name": "NIO Inc ADR",
      "percent": "1.507"
    },
    {
      "ticker": "1211 HK",
      "name": "BYD Co Ltd",
      "percent": "1.489"
    },
    {
      "ticker": "LAC",
      "name": "Lithium Americas Corp",
      "percent": "1.459"
    },
    {
      "ticker": "AMRC",
      "name": "Ameresco Inc",
      "percent": "1.380"
    },
    {
      "ticker": "SSO",
      "name": "Scatec Solar ASA",
      "percent": "1.362"
    },
    {
      "ticker": "2208 HK",
      "name": "Xinjiang Goldwind Science & Technology Co Ltd",
      "percent": "1.340"
    },
    {
      "ticker": "968 HK",
      "name": "Xinyi Solar Holdings Ltd",
      "percent": "1.333"
    },
    {
      "ticker": "PLUG",
      "name": "Plug Power Inc",
      "percent": "1.318"
    },
    {
      "ticker": "CWR LN",
      "name": "Ceres Power Holdings PLC",
      "percent": "1.317"
    },
    {
      "ticker": "VBK",
      "name": "VERBIO Vereinigte BioEnergie AG",
      "percent": "1.312"
    },
    {
      "ticker": "3868 HK",
      "name": "Xinyi Energy Holdings Ltd",
      "percent": "1.309"
    },
    {
      "ticker": "XBC",
      "name": "Xebec Adsorption Inc",
      "percent": "1.291"
    },
    {
      "ticker": "BE",
      "name": "Bloom Energy Corp",
      "percent": "1.278"
    },
    {
      "ticker": "REGI",
      "name": "Renewable Energy Group Inc",
      "percent": "1.276"
    },
    {
      "ticker": "TPIC",
      "name": "TPI Composites Inc",
      "percent": "1.261"
    },
    {
      "ticker": "BLX",
      "name": "Boralex Inc",
      "percent": "1.252"
    },
    {
      "ticker": "CSIQ",
      "name": "Canadian Solar Inc",
      "percent": "1.249"
    },
    {
      "ticker": "ORA",
      "name": "Ormat Technologies Inc",
      "percent": "1.231"
    },
    {
      "ticker": "BLDP",
      "name": "Ballard Power Systems Inc",
      "percent": "1.229"
    },
    {
      "ticker": "ITRI",
      "name": "Itron Inc",
      "percent": "1.218"
    },
    {
      "ticker": "SLR",
      "name": "Solaria Energia y Medio Ambiente SA",
      "percent": "1.216"
    },
    {
      "ticker": "9519 JP",
      "name": "RENOVA Inc",
      "percent": "1.204"
    },
    {
      "ticker": "LIGHT",
      "name": "Signify NV",
      "percent": "1.194"
    },
    {
      "ticker": "INE",
      "name": "Innergex Renewable Energy Inc",
      "percent": "1.192"
    },
    {
      "ticker": "CAP",
      "name": "Encavis AG",
      "percent": "1.187"
    },
    {
      "ticker": "EDPR",
      "name": "EDP Renovaveis SA",
      "percent": "1.183"
    },
    {
      "ticker": "ORSTED DC",
      "name": "Orsted A/S",
      "percent": "1.174"
    },
    {
      "ticker": "VWS DC",
      "name": "Vestas Wind Systems A/S",
      "percent": "1.174"
    },
    {
      "ticker": "NDX1",
      "name": "Nordex SE",
      "percent": "1.173"
    },
    {
      "ticker": "9517 JP",
      "name": "eRex Co Ltd",
      "percent": "1.171"
    },
    {
      "ticker": "FSLR",
      "name": "First Solar Inc",
      "percent": "1.167"
    },
    {
      "ticker": "NOVA",
      "name": "Sunnova Energy International Inc",
      "percent": "1.151"
    },
    {
      "ticker": "RNW",
      "name": "TransAlta Renewables Inc",
      "percent": "1.145"
    },
    {
      "ticker": "VER AV",
      "name": "Verbund AG",
      "percent": "1.139"
    },
    {
      "ticker": "SGRE",
      "name": "Siemens Gamesa Renewable Energy SA",
      "percent": "1.139"
    },
    {
      "ticker": "CREE",
      "name": "Cree Inc",
      "percent": "1.128"
    },
    {
      "ticker": "OLED",
      "name": "Universal Display Corp",
      "percent": "1.124"
    },
    {
      "ticker": "ITM LN",
      "name": "ITM Power PLC",
      "percent": "1.119"
    },
    {
      "ticker": "VECO",
      "name": "Veeco Instruments Inc",
      "percent": "1.115"
    },
    {
      "ticker": "MEL",
      "name": "Meridian Energy Ltd",
      "percent": "1.113"
    },
    {
      "ticker": "S92",
      "name": "SMA Solar Technology AG",
      "percent": "1.107"
    },
    {
      "ticker": "ACA",
      "name": "Arcosa Inc",
      "percent": "1.099"
    },
    {
      "ticker": "PNE3",
      "name": "PNE AG",
      "percent": "1.098"
    },
    {
      "ticker": "WLDN",
      "name": "Willdan Group Inc",
      "percent": "1.092"
    },
    {
      "ticker": "HASI",
      "name": "Hannon Armstrong Sustainable Infrastructure Capital Inc",
      "percent": "1.089"
    },
    {
      "ticker": "PCELL SS",
      "name": "PowerCell Sweden AB",
      "percent": "1.078"
    },
    {
      "ticker": "KSP",
      "name": "Kingspan Group PLC",
      "percent": "1.071"
    },
    {
      "ticker": "NEOEN FP",
      "name": "Neoen SA",
      "percent": "1.069"
    },
    {
      "ticker": "EOLUB SS",
      "name": "Eolus Vind AB",
      "percent": "1.068"
    },
    {
      "ticker": "GUR SW",
      "name": "Gurit Holding AG",
      "percent": "1.061"
    },
    {
      "ticker": "TLT",
      "name": "Tilt Renewables Ltd",
      "percent": "1.056"
    },
    {
      "ticker": "XPEV",
      "name": "XPeng Inc ADR",
      "percent": "1.054"
    },
    {
      "ticker": "RUN",
      "name": "Sunrun Inc",
      "percent": "1.047"
    },
    {
      "ticker": "PRY",
      "name": "Prysmian SpA",
      "percent": "1.045"
    },
    {
      "ticker": "CAV1V FH",
      "name": "Caverion Oyj",
      "percent": "1.043"
    },
    {
      "ticker": "2393 TT",
      "name": "Everlight Electronics Co Ltd",
      "percent": "1.041"
    },
    {
      "ticker": "1407 JP",
      "name": "West Holdings Corp",
      "percent": "1.032"
    },
    {
      "ticker": "SQM",
      "name": "Sociedad Quimica y Minera de Chile SA ADR",
      "percent": "1.027"
    },
    {
      "ticker": "NIBEB SS",
      "name": "Nibe Industrier AB",
      "percent": "1.027"
    },
    {
      "ticker": "FCEL",
      "name": "FuelCell Energy Inc",
      "percent": "1.022"
    },
    {
      "ticker": "5483 TT",
      "name": "Sino-American Silicon Products Inc",
      "percent": "1.015"
    },
    {
      "ticker": "MCY",
      "name": "Mercury NZ Ltd",
      "percent": "1.015"
    },
    {
      "ticker": "CE2",
      "name": "CropEnergies AG",
      "percent": "1.015"
    },
    {
      "ticker": "GREEN SW",
      "name": "Credit Suisse Real Estate Fund Green Property",
      "percent": "1.011"
    },
    {
      "ticker": "UKW LN",
      "name": "Greencoat UK Wind PLC/Funds",
      "percent": "1.010"
    },
    {
      "ticker": "ABIO FP",
      "name": "Albioma SA",
      "percent": "1.009"
    },
    {
      "ticker": "AZRE",
      "name": "Azure Power Global Ltd",
      "percent": "1.008"
    },
    {
      "ticker": "TRIG LN",
      "name": "Renewables Infrastructure Group Ltd/The",
      "percent": "1.001"
    },
    {
      "ticker": "NEL",
      "name": "NEL ASA",
      "percent": "0.991"
    },
    {
      "ticker": "LAND SW",
      "name": "Landis+Gyr Group AG",
      "percent": "0.988"
    },
    {
      "ticker": "TRN",
      "name": "Terna Rete Elettrica Nazionale SpA",
      "percent": "0.986"
    },
    {
      "ticker": "006400 KS",
      "name": "Samsung SDI Co Ltd",
      "percent": "0.985"
    },
    {
      "ticker": "NZYMB DC",
      "name": "Novozymes A/S",
      "percent": "0.984"
    },
    {
      "ticker": "6674 JP",
      "name": "GS Yuasa Corp",
      "percent": "0.979"
    },
    {
      "ticker": "ANA",
      "name": "Acciona SA",
      "percent": "0.963"
    },
    {
      "ticker": "MAXN",
      "name": "Maxeon Solar Technologies Ltd",
      "percent": "0.952"
    },
    {
      "ticker": "MCPHY FP",
      "name": "McPhy Energy SA",
      "percent": "0.949"
    },
    {
      "ticker": "112610 KS",
      "name": "CS Wind Corp",
      "percent": "0.945"
    },
    {
      "ticker": "FKR",
      "name": "Falck Renewables SpA",
      "percent": "0.942"
    },
    {
      "ticker": "086520 KS",
      "name": "Ecopro Co Ltd",
      "percent": "0.913"
    },
    {
      "ticker": "AGPXX",
      "name": "STIT - Government & Agency Portfolio",
      "percent": "0.052"
    },
    {
      "ticker": "-Taiwan",
      "name": "Cash/Receivables/Payables",
      "percent": "0.039"
    },
    {
      "ticker": "-NewZealnd",
      "name": "Cash/Receivables/Payables",
      "percent": "0.017"
    },
    {
      "ticker": "-GBP-",
      "name": "Cash/Receivables/Payables",
      "percent": "0.006"
    },
    {
      "ticker": "-Canadian",
      "name": "Cash/Receivables/Payables",
      "percent": "0.003"
    },
    {
      "ticker": "-HongKong",
      "name": "Cash/Receivables/Payables",
      "percent": "0.000"
    },
    {
      "ticker": "-BrazilRea",
      "name": "Cash/Receivables/Payables",
      "percent": "0.000"
    },
    {
      "ticker": "-CASH-",
      "name": "Cash/Receivables/Payables",
      "percent": "0.000"
    },
    {
      "ticker": "-JapanYen-",
      "name": "Cash/Receivables/Payables",
      "percent": "-0.000"
    },
    {
      "ticker": "-DenmarkKr",
      "name": "Cash/Receivables/Payables",
      "percent": "-0.000"
    },
    {
      "ticker": "-SwedKrona",
      "name": "Cash/Receivables/Payables",
      "percent": "-0.000"
    },
    {
      "ticker": "-SwissFran",
      "name": "Cash/Receivables/Payables",
      "percent": "-0.000"
    },
    {
      "ticker": "-NorwayKrn",
      "name": "Cash/Receivables/Payables",
      "percent": "-0.000"
    },
    {
      "ticker": "-Euro-",
      "name": "Cash/Receivables/Payables",
      "percent": "-0.001"
    }
  ]
}