{
  "name": "S&P 500® Top 50 ETF",
  "ticker": "XLG",
  "Inception": "5/4/2005",
  "Gross Exp. Ratio": "0.20%",
  "YTD": "13.66",
  "1Yr": "25.51",
  "3Yr": "15.81",
  "5Yr": "16.72",
  "10Yr": "14.58",
  "Since Incept.": "9.29",
  "Category": "SP Factor",
  "SubCategory": "Size",
  "infer": "invesco",
  "issuer": "Invesco",
  "website": "https://www.invesco.com/us/financial-products/etfs/product-detail?audienceType=Investor&ticker=XLG",
  "holdingDataSource": {
    "url": "https://www.invesco.com/us/financial-products/etfs/holdings/main/holdings/0?audienceType=Investor&action=download&ticker=XLG",
    "fileExt": "csv",
    "transform": "invesco"
  },
  "holdings": [
    {
      "Fund Ticker": "XLG",
      "Security Identifier": "037833100",
      "Holding Ticker": "AAPL",
      "Shares/Par Value": "1,674,366",
      "MarketValue": "202,765,722.60",
      "Weight": "12.060",
      "Name": "Apple Inc",
      "Class of Shares": "Common Stock",
      "Sector": "Information Technology",
      "Date": "10/13/2020",
      "ticker": "AAPL",
      "name": "Apple Inc",
      "percent": "12.060",
      "weight": 0.1206
    },
    {
      "Fund Ticker": "XLG",
      "Security Identifier": "594918104",
      "Holding Ticker": "MSFT",
      "Shares/Par Value": "787,889",
      "MarketValue": "175,588,942.54",
      "Weight": "10.443",
      "Name": "Microsoft Corp",
      "Class of Shares": "Common Stock",
      "Sector": "Information Technology",
      "Date": "10/13/2020",
      "ticker": "MSFT",
      "name": "Microsoft Corp",
      "percent": "10.443",
      "weight": 0.10443
    },
    {
      "Fund Ticker": "XLG",
      "Security Identifier": "023135106",
      "Holding Ticker": "AMZN",
      "Shares/Par Value": "44,327",
      "MarketValue": "152,645,787.01",
      "Weight": "9.079",
      "Name": "Amazon.com Inc",
      "Class of Shares": "Common Stock",
      "Sector": "Consumer Discretionary",
      "Date": "10/13/2020",
      "ticker": "AMZN",
      "name": "Amazon.com Inc",
      "percent": "9.079",
      "weight": 0.09079
    },
    {
      "Fund Ticker": "XLG",
      "Security Identifier": "30303M102",
      "Holding Ticker": "FB",
      "Shares/Par Value": "250,316",
      "MarketValue": "69,122,260.24",
      "Weight": "4.111",
      "Name": "Facebook Inc",
      "Class of Shares": "Common Stock",
      "Sector": "Communication Services",
      "Date": "10/13/2020",
      "ticker": "FB",
      "name": "Facebook Inc",
      "percent": "4.111",
      "weight": 0.04111
    },
    {
      "Fund Ticker": "XLG",
      "Security Identifier": "02079K305",
      "Holding Ticker": "GOOGL",
      "Shares/Par Value": "31,283",
      "MarketValue": "49,022,650.81",
      "Weight": "2.916",
      "Name": "Alphabet Inc",
      "Class of Shares": "Common Stock",
      "Sector": "Communication Services",
      "Date": "10/13/2020",
      "ticker": "GOOGL",
      "name": "Alphabet Inc",
      "percent": "2.916",
      "weight": 0.02916
    },
    {
      "Fund Ticker": "XLG",
      "Security Identifier": "02079K107",
      "Holding Ticker": "GOOG",
      "Shares/Par Value": "30,567",
      "MarketValue": "48,041,542.56",
      "Weight": "2.857",
      "Name": "Alphabet Inc",
      "Class of Shares": "Common Stock",
      "Sector": "Communication Services",
      "Date": "10/13/2020",
      "ticker": "GOOG",
      "name": "Alphabet Inc",
      "percent": "2.857",
      "weight": 0.02857
    },
    {
      "Fund Ticker": "XLG",
      "Security Identifier": "084670702",
      "Holding Ticker": "BRK/B",
      "Shares/Par Value": "206,374",
      "MarketValue": "43,815,263.94",
      "Weight": "2.606",
      "Name": "Berkshire Hathaway Inc",
      "Class of Shares": "Common Stock",
      "Sector": "Financials",
      "Date": "10/13/2020",
      "ticker": "BRK/B",
      "name": "Berkshire Hathaway Inc",
      "percent": "2.606",
      "weight": 0.02606
    },
    {
      "Fund Ticker": "XLG",
      "Security Identifier": "478160104",
      "Holding Ticker": "JNJ",
      "Shares/Par Value": "274,110",
      "MarketValue": "40,666,959.60",
      "Weight": "2.419",
      "Name": "Johnson & Johnson",
      "Class of Shares": "Common Stock",
      "Sector": "Health Care",
      "Date": "10/13/2020",
      "ticker": "JNJ",
      "name": "Johnson & Johnson",
      "percent": "2.419",
      "weight": 0.02419
    },
    {
      "Fund Ticker": "XLG",
      "Security Identifier": "742718109",
      "Holding Ticker": "PG",
      "Shares/Par Value": "259,201",
      "MarketValue": "37,379,376.21",
      "Weight": "2.223",
      "Name": "Procter & Gamble Co/The",
      "Class of Shares": "Common Stock",
      "Sector": "Consumer Staples",
      "Date": "10/13/2020",
      "ticker": "PG",
      "name": "Procter & Gamble Co/The",
      "percent": "2.223",
      "weight": 0.02223
    },
    {
      "Fund Ticker": "XLG",
      "Security Identifier": "67066G104",
      "Holding Ticker": "NVDA",
      "Shares/Par Value": "64,238",
      "MarketValue": "36,611,163.34",
      "Weight": "2.177",
      "Name": "NVIDIA Corp",
      "Class of Shares": "Common Stock",
      "Sector": "Information Technology",
      "Date": "10/13/2020",
      "ticker": "NVDA",
      "name": "NVIDIA Corp",
      "percent": "2.177",
      "weight": 0.02177
    },
    {
      "Fund Ticker": "XLG",
      "Security Identifier": "92826C839",
      "Holding Ticker": "V",
      "Shares/Par Value": "175,535",
      "MarketValue": "35,865,311.20",
      "Weight": "2.133",
      "Name": "Visa Inc",
      "Class of Shares": "Common Stock",
      "Sector": "Information Technology",
      "Date": "10/13/2020",
      "ticker": "V",
      "name": "Visa Inc",
      "percent": "2.133",
      "weight": 0.02133
    },
    {
      "Fund Ticker": "XLG",
      "Security Identifier": "91324P102",
      "Holding Ticker": "UNH",
      "Shares/Par Value": "98,942",
      "MarketValue": "32,791,357.64",
      "Weight": "1.950",
      "Name": "UnitedHealth Group Inc",
      "Class of Shares": "Common Stock",
      "Sector": "Health Care",
      "Date": "10/13/2020",
      "ticker": "UNH",
      "name": "UnitedHealth Group Inc",
      "percent": "1.950",
      "weight": 0.0195
    },
    {
      "Fund Ticker": "XLG",
      "Security Identifier": "437076102",
      "Holding Ticker": "HD",
      "Shares/Par Value": "112,073",
      "MarketValue": "32,541,516.28",
      "Weight": "1.935",
      "Name": "Home Depot Inc/The",
      "Class of Shares": "Common Stock",
      "Sector": "Consumer Discretionary",
      "Date": "10/13/2020",
      "ticker": "HD",
      "name": "Home Depot Inc/The",
      "percent": "1.935",
      "weight": 0.01935
    },
    {
      "Fund Ticker": "XLG",
      "Security Identifier": "46625H100",
      "Holding Ticker": "JPM",
      "Shares/Par Value": "317,294",
      "MarketValue": "31,976,889.32",
      "Weight": "1.902",
      "Name": "JPMorgan Chase & Co",
      "Class of Shares": "Common Stock",
      "Sector": "Financials",
      "Date": "10/13/2020",
      "ticker": "JPM",
      "name": "JPMorgan Chase & Co",
      "percent": "1.902",
      "weight": 0.01902
    },
    {
      "Fund Ticker": "XLG",
      "Security Identifier": "57636Q104",
      "Holding Ticker": "MA",
      "Shares/Par Value": "91,969",
      "MarketValue": "31,806,558.96",
      "Weight": "1.892",
      "Name": "Mastercard Inc",
      "Class of Shares": "Common Stock",
      "Sector": "Information Technology",
      "Date": "10/13/2020",
      "ticker": "MA",
      "name": "Mastercard Inc",
      "percent": "1.892",
      "weight": 0.01892
    },
    {
      "Fund Ticker": "XLG",
      "Security Identifier": "00724F101",
      "Holding Ticker": "ADBE",
      "Shares/Par Value": "49,939",
      "MarketValue": "25,684,127.09",
      "Weight": "1.528",
      "Name": "Adobe Inc",
      "Class of Shares": "Common Stock",
      "Sector": "Information Technology",
      "Date": "10/13/2020",
      "ticker": "ADBE",
      "name": "Adobe Inc",
      "percent": "1.528",
      "weight": 0.01528
    },
    {
      "Fund Ticker": "XLG",
      "Security Identifier": "92343V104",
      "Holding Ticker": "VZ",
      "Shares/Par Value": "430,824",
      "MarketValue": "25,573,712.64",
      "Weight": "1.521",
      "Name": "Verizon Communications Inc",
      "Class of Shares": "Common Stock",
      "Sector": "Communication Services",
      "Date": "10/13/2020",
      "ticker": "VZ",
      "name": "Verizon Communications Inc",
      "percent": "1.521",
      "weight": 0.01521
    },
    {
      "Fund Ticker": "XLG",
      "Security Identifier": "64110L106",
      "Holding Ticker": "NFLX",
      "Shares/Par Value": "45,915",
      "MarketValue": "25,441,042.35",
      "Weight": "1.513",
      "Name": "Netflix Inc",
      "Class of Shares": "Common Stock",
      "Sector": "Communication Services",
      "Date": "10/13/2020",
      "ticker": "NFLX",
      "name": "Netflix Inc",
      "percent": "1.513",
      "weight": 0.01513
    },
    {
      "Fund Ticker": "XLG",
      "Security Identifier": "70450Y103",
      "Holding Ticker": "PYPL",
      "Shares/Par Value": "122,155",
      "MarketValue": "25,376,479.70",
      "Weight": "1.509",
      "Name": "PayPal Holdings Inc",
      "Class of Shares": "Common Stock",
      "Sector": "Information Technology",
      "Date": "10/13/2020",
      "ticker": "PYPL",
      "name": "PayPal Holdings Inc",
      "percent": "1.509",
      "weight": 0.01509
    },
    {
      "Fund Ticker": "XLG",
      "Security Identifier": "79466L302",
      "Holding Ticker": "CRM",
      "Shares/Par Value": "94,743",
      "MarketValue": "25,280,274.69",
      "Weight": "1.504",
      "Name": "salesforce.com Inc",
      "Class of Shares": "Common Stock",
      "Sector": "Information Technology",
      "Date": "10/13/2020",
      "ticker": "CRM",
      "name": "salesforce.com Inc",
      "percent": "1.504",
      "weight": 0.01504
    },
    {
      "Fund Ticker": "XLG",
      "Security Identifier": "254687106",
      "Holding Ticker": "DIS",
      "Shares/Par Value": "188,138",
      "MarketValue": "24,262,276.48",
      "Weight": "1.443",
      "Name": "Walt Disney Co/The",
      "Class of Shares": "Common Stock",
      "Sector": "Communication Services",
      "Date": "10/13/2020",
      "ticker": "DIS",
      "name": "Walt Disney Co/The",
      "percent": "1.443",
      "weight": 0.01443
    },
    {
      "Fund Ticker": "XLG",
      "Security Identifier": "458140100",
      "Holding Ticker": "INTC",
      "Shares/Par Value": "442,791",
      "MarketValue": "23,835,439.53",
      "Weight": "1.418",
      "Name": "Intel Corp",
      "Class of Shares": "Common Stock",
      "Sector": "Information Technology",
      "Date": "10/13/2020",
      "ticker": "INTC",
      "name": "Intel Corp",
      "percent": "1.418",
      "weight": 0.01418
    },
    {
      "Fund Ticker": "XLG",
      "Security Identifier": "20030N101",
      "Holding Ticker": "CMCSA",
      "Shares/Par Value": "474,614",
      "MarketValue": "21,780,036.46",
      "Weight": "1.295",
      "Name": "Comcast Corp",
      "Class of Shares": "Common Stock",
      "Sector": "Communication Services",
      "Date": "10/13/2020",
      "ticker": "CMCSA",
      "name": "Comcast Corp",
      "percent": "1.295",
      "weight": 0.01295
    },
    {
      "Fund Ticker": "XLG",
      "Security Identifier": "717081103",
      "Holding Ticker": "PFE",
      "Shares/Par Value": "578,542",
      "MarketValue": "21,348,199.80",
      "Weight": "1.270",
      "Name": "Pfizer Inc",
      "Class of Shares": "Common Stock",
      "Sector": "Health Care",
      "Date": "10/13/2020",
      "ticker": "PFE",
      "name": "Pfizer Inc",
      "percent": "1.270",
      "weight": 0.0127
    },
    {
      "Fund Ticker": "XLG",
      "Security Identifier": "58933Y105",
      "Holding Ticker": "MRK",
      "Shares/Par Value": "263,326",
      "MarketValue": "21,253,041.46",
      "Weight": "1.264",
      "Name": "Merck & Co Inc",
      "Class of Shares": "Common Stock",
      "Sector": "Health Care",
      "Date": "10/13/2020",
      "ticker": "MRK",
      "name": "Merck & Co Inc",
      "percent": "1.264",
      "weight": 0.01264
    },
    {
      "Fund Ticker": "XLG",
      "Security Identifier": "931142103",
      "Holding Ticker": "WMT",
      "Shares/Par Value": "144,564",
      "MarketValue": "21,139,593.72",
      "Weight": "1.257",
      "Name": "Walmart Inc",
      "Class of Shares": "Common Stock",
      "Sector": "Consumer Staples",
      "Date": "10/13/2020",
      "ticker": "WMT",
      "name": "Walmart Inc",
      "percent": "1.257",
      "weight": 0.01257
    },
    {
      "Fund Ticker": "XLG",
      "Security Identifier": "713448108",
      "Holding Ticker": "PEP",
      "Shares/Par Value": "144,158",
      "MarketValue": "20,692,439.32",
      "Weight": "1.231",
      "Name": "PepsiCo Inc",
      "Class of Shares": "Common Stock",
      "Sector": "Consumer Staples",
      "Date": "10/13/2020",
      "ticker": "PEP",
      "name": "PepsiCo Inc",
      "percent": "1.231",
      "weight": 0.01231
    },
    {
      "Fund Ticker": "XLG",
      "Security Identifier": "00206R102",
      "Holding Ticker": "T",
      "Shares/Par Value": "741,803",
      "MarketValue": "20,585,033.25",
      "Weight": "1.224",
      "Name": "AT&T Inc",
      "Class of Shares": "Common Stock",
      "Sector": "Communication Services",
      "Date": "10/13/2020",
      "ticker": "T",
      "name": "AT&T Inc",
      "percent": "1.224",
      "weight": 0.01224
    },
    {
      "Fund Ticker": "XLG",
      "Security Identifier": "191216100",
      "Holding Ticker": "KO",
      "Shares/Par Value": "402,489",
      "MarketValue": "20,212,997.58",
      "Weight": "1.202",
      "Name": "Coca-Cola Co/The",
      "Class of Shares": "Common Stock",
      "Sector": "Consumer Staples",
      "Date": "10/13/2020",
      "ticker": "KO",
      "name": "Coca-Cola Co/The",
      "percent": "1.202",
      "weight": 0.01202
    },
    {
      "Fund Ticker": "XLG",
      "Security Identifier": "002824100",
      "Holding Ticker": "ABT",
      "Shares/Par Value": "184,335",
      "MarketValue": "19,976,383.95",
      "Weight": "1.188",
      "Name": "Abbott Laboratories",
      "Class of Shares": "Common Stock",
      "Sector": "Health Care",
      "Date": "10/13/2020",
      "ticker": "ABT",
      "name": "Abbott Laboratories",
      "percent": "1.188",
      "weight": 0.01188
    },
    {
      "Fund Ticker": "XLG",
      "Security Identifier": "060505104",
      "Holding Ticker": "BAC",
      "Shares/Par Value": "793,797",
      "MarketValue": "19,805,235.15",
      "Weight": "1.178",
      "Name": "Bank of America Corp",
      "Class of Shares": "Common Stock",
      "Sector": "Financials",
      "Date": "10/13/2020",
      "ticker": "BAC",
      "name": "Bank of America Corp",
      "percent": "1.178",
      "weight": 0.01178
    },
    {
      "Fund Ticker": "XLG",
      "Security Identifier": "883556102",
      "Holding Ticker": "TMO",
      "Shares/Par Value": "41,186",
      "MarketValue": "19,255,690.58",
      "Weight": "1.145",
      "Name": "Thermo Fisher Scientific Inc",
      "Class of Shares": "Common Stock",
      "Sector": "Health Care",
      "Date": "10/13/2020",
      "ticker": "TMO",
      "name": "Thermo Fisher Scientific Inc",
      "percent": "1.145",
      "weight": 0.01145
    },
    {
      "Fund Ticker": "XLG",
      "Security Identifier": "580135101",
      "Holding Ticker": "MCD",
      "Shares/Par Value": "77,471",
      "MarketValue": "17,613,031.85",
      "Weight": "1.048",
      "Name": "McDonald's Corp",
      "Class of Shares": "Common Stock",
      "Sector": "Consumer Discretionary",
      "Date": "10/13/2020",
      "ticker": "MCD",
      "name": "McDonald's Corp",
      "percent": "1.048",
      "weight": 0.01048
    },
    {
      "Fund Ticker": "XLG",
      "Security Identifier": "17275R102",
      "Holding Ticker": "CSCO",
      "Shares/Par Value": "440,753",
      "MarketValue": "17,546,376.93",
      "Weight": "1.044",
      "Name": "Cisco Systems Inc",
      "Class of Shares": "Common Stock",
      "Sector": "Information Technology",
      "Date": "10/13/2020",
      "ticker": "CSCO",
      "name": "Cisco Systems Inc",
      "percent": "1.044",
      "weight": 0.01044
    },
    {
      "Fund Ticker": "XLG",
      "Security Identifier": "22160K105",
      "Holding Ticker": "COST",
      "Shares/Par Value": "45,968",
      "MarketValue": "17,499,098.24",
      "Weight": "1.041",
      "Name": "Costco Wholesale Corp",
      "Class of Shares": "Common Stock",
      "Sector": "Consumer Staples",
      "Date": "10/13/2020",
      "ticker": "COST",
      "name": "Costco Wholesale Corp",
      "percent": "1.041",
      "weight": 0.01041
    },
    {
      "Fund Ticker": "XLG",
      "Security Identifier": "654106103",
      "Holding Ticker": "NKE",
      "Shares/Par Value": "129,607",
      "MarketValue": "16,745,224.40",
      "Weight": "0.996",
      "Name": "NIKE Inc",
      "Class of Shares": "Common Stock",
      "Sector": "Consumer Discretionary",
      "Date": "10/13/2020",
      "ticker": "NKE",
      "name": "NIKE Inc",
      "percent": "0.996",
      "weight": 0.00996
    },
    {
      "Fund Ticker": "XLG",
      "Security Identifier": "00287Y109",
      "Holding Ticker": "ABBV",
      "Shares/Par Value": "183,741",
      "MarketValue": "16,137,972.03",
      "Weight": "0.960",
      "Name": "AbbVie Inc",
      "Class of Shares": "Common Stock",
      "Sector": "Health Care",
      "Date": "10/13/2020",
      "ticker": "ABBV",
      "name": "AbbVie Inc",
      "percent": "0.960",
      "weight": 0.0096
    },
    {
      "Fund Ticker": "XLG",
      "Security Identifier": "11135F101",
      "Holding Ticker": "AVGO",
      "Shares/Par Value": "41,873",
      "MarketValue": "15,974,130.77",
      "Weight": "0.950",
      "Name": "Broadcom Inc",
      "Class of Shares": "Common Stock",
      "Sector": "Information Technology",
      "Date": "10/13/2020",
      "ticker": "AVGO",
      "name": "Broadcom Inc",
      "percent": "0.950",
      "weight": 0.0095
    },
    {
      "Fund Ticker": "XLG",
      "Security Identifier": "65339F101",
      "Holding Ticker": "NEE",
      "Shares/Par Value": "50,979",
      "MarketValue": "15,368,639.13",
      "Weight": "0.914",
      "Name": "NextEra Energy Inc",
      "Class of Shares": "Common Stock",
      "Sector": "Utilities",
      "Date": "10/13/2020",
      "ticker": "NEE",
      "name": "NextEra Energy Inc",
      "percent": "0.914",
      "weight": 0.00914
    },
    {
      "Fund Ticker": "XLG",
      "Security Identifier": "G1151C101",
      "Holding Ticker": "ACN",
      "Shares/Par Value": "66,236",
      "MarketValue": "15,193,213.68",
      "Weight": "0.904",
      "Name": "Accenture PLC",
      "Class of Shares": "Common Stock",
      "Sector": "Information Technology",
      "Date": "10/13/2020",
      "ticker": "ACN",
      "name": "Accenture PLC",
      "percent": "0.904",
      "weight": 0.00904
    },
    {
      "Fund Ticker": "XLG",
      "Security Identifier": "30231G102",
      "Holding Ticker": "XOM",
      "Shares/Par Value": "440,213",
      "MarketValue": "15,064,088.86",
      "Weight": "0.896",
      "Name": "Exxon Mobil Corp",
      "Class of Shares": "Common Stock",
      "Sector": "Energy",
      "Date": "10/13/2020",
      "ticker": "XOM",
      "name": "Exxon Mobil Corp",
      "percent": "0.896",
      "weight": 0.00896
    },
    {
      "Fund Ticker": "XLG",
      "Security Identifier": "G5960L103",
      "Holding Ticker": "MDT",
      "Shares/Par Value": "139,950",
      "MarketValue": "14,966,253.00",
      "Weight": "0.890",
      "Name": "Medtronic PLC",
      "Class of Shares": "Common Stock",
      "Sector": "Health Care",
      "Date": "10/13/2020",
      "ticker": "MDT",
      "name": "Medtronic PLC",
      "percent": "0.890",
      "weight": 0.0089
    },
    {
      "Fund Ticker": "XLG",
      "Security Identifier": "166764100",
      "Holding Ticker": "CVX",
      "Shares/Par Value": "200,504",
      "MarketValue": "14,716,993.60",
      "Weight": "0.875",
      "Name": "Chevron Corp",
      "Class of Shares": "Common Stock",
      "Sector": "Energy",
      "Date": "10/13/2020",
      "ticker": "CVX",
      "name": "Chevron Corp",
      "percent": "0.875",
      "weight": 0.00875
    },
    {
      "Fund Ticker": "XLG",
      "Security Identifier": "031162100",
      "Holding Ticker": "AMGN",
      "Shares/Par Value": "60,978",
      "MarketValue": "14,594,474.52",
      "Weight": "0.868",
      "Name": "Amgen Inc",
      "Class of Shares": "Common Stock",
      "Sector": "Health Care",
      "Date": "10/13/2020",
      "ticker": "AMGN",
      "name": "Amgen Inc",
      "percent": "0.868",
      "weight": 0.00868
    },
    {
      "Fund Ticker": "XLG",
      "Security Identifier": "907818108",
      "Holding Ticker": "UNP",
      "Shares/Par Value": "70,676",
      "MarketValue": "14,347,228.00",
      "Weight": "0.853",
      "Name": "Union Pacific Corp",
      "Class of Shares": "Common Stock",
      "Sector": "Industrials",
      "Date": "10/13/2020",
      "ticker": "UNP",
      "name": "Union Pacific Corp",
      "percent": "0.853",
      "weight": 0.00853
    },
    {
      "Fund Ticker": "XLG",
      "Security Identifier": "110122108",
      "Holding Ticker": "BMY",
      "Shares/Par Value": "234,663",
      "MarketValue": "14,344,949.19",
      "Weight": "0.853",
      "Name": "Bristol Myers Squibb Co",
      "Class of Shares": "Common Stock",
      "Sector": "Health Care",
      "Date": "10/13/2020",
      "ticker": "BMY",
      "name": "Bristol Myers Squibb Co",
      "percent": "0.853",
      "weight": 0.00853
    },
    {
      "Fund Ticker": "XLG",
      "Security Identifier": "718172109",
      "Holding Ticker": "PM",
      "Shares/Par Value": "162,133",
      "MarketValue": "12,842,554.93",
      "Weight": "0.764",
      "Name": "Philip Morris International Inc",
      "Class of Shares": "Common Stock",
      "Sector": "Consumer Staples",
      "Date": "10/13/2020",
      "ticker": "PM",
      "name": "Philip Morris International Inc",
      "percent": "0.764",
      "weight": 0.00764
    },
    {
      "Fund Ticker": "XLG",
      "Security Identifier": "532457108",
      "Holding Ticker": "LLY",
      "Shares/Par Value": "82,652",
      "MarketValue": "12,404,412.16",
      "Weight": "0.738",
      "Name": "Eli Lilly and Co",
      "Class of Shares": "Common Stock",
      "Sector": "Health Care",
      "Date": "10/13/2020",
      "ticker": "LLY",
      "name": "Eli Lilly and Co",
      "percent": "0.738",
      "weight": 0.00738
    },
    {
      "Fund Ticker": "XLG",
      "Security Identifier": "68389X105",
      "Holding Ticker": "ORCL",
      "Shares/Par Value": "201,278",
      "MarketValue": "12,271,919.66",
      "Weight": "0.730",
      "Name": "Oracle Corp",
      "Class of Shares": "Common Stock",
      "Sector": "Information Technology",
      "Date": "10/13/2020",
      "ticker": "ORCL",
      "name": "Oracle Corp",
      "percent": "0.730",
      "weight": 0.0073
    },
    {
      "Fund Ticker": "XLG",
      "Security Identifier": "459200101",
      "Holding Ticker": "IBM",
      "Shares/Par Value": "92,721",
      "MarketValue": "11,599,397.10",
      "Weight": "0.690",
      "Name": "International Business Machines Corp",
      "Class of Shares": "Common Stock",
      "Sector": "Information Technology",
      "Date": "10/13/2020",
      "ticker": "IBM",
      "name": "International Business Machines Corp",
      "percent": "0.690",
      "weight": 0.0069
    },
    {
      "Fund Ticker": "XLG",
      "Security Identifier": "172967424",
      "Holding Ticker": "C",
      "Shares/Par Value": "216,749",
      "MarketValue": "9,467,596.32",
      "Weight": "0.563",
      "Name": "Citigroup Inc",
      "Class of Shares": "Common Stock",
      "Sector": "Financials",
      "Date": "10/13/2020",
      "ticker": "C",
      "name": "Citigroup Inc",
      "percent": "0.563",
      "weight": 0.00563
    },
    {
      "Fund Ticker": "XLG",
      "Security Identifier": "825252885",
      "Holding Ticker": "AGPXX",
      "Shares/Par Value": "512,055",
      "MarketValue": "512,054.90",
      "Weight": "0.030",
      "Name": "STIT - Government & Agency Portfolio",
      "Class of Shares": "Money Market Fund, Taxable",
      "Sector": "Investment Companies",
      "Date": "10/13/2020",
      "ticker": "AGPXX",
      "name": "STIT - Government & Agency Portfolio",
      "percent": "0.030",
      "weight": 0.0003
    },
    {
      "Fund Ticker": "",
      "weight": null
    }
  ]
}